{
    "klass": "Specie",
    "id": 330,
    "dbSymbol": "flygon",
    "forms": [
        {
            "form": 0,
            "height": 2.0,
            "weight": 82.0,
            "type1": "ground",
            "type2": "dragon",
            "baseHp": 80,
            "baseAtk": 100,
            "baseDfe": 80,
            "baseSpd": 100,
            "baseAts": 80,
            "baseDfs": 80,
            "evHp": 0,
            "evAtk": 0,
            "evDfe": 0,
            "evSpd": 0,
            "evAts": 0,
            "evDfs": 0,
            "evolutions": [],
            "experienceType": 3,
            "baseExperience": 234,
            "baseLoyalty": 50,
            "catchRate": 45,
            "femaleRate": 50.0,
            "breedGroups": [
                3,
                14
            ],
            "hatchSteps": 2560,
            "babyDbSymbol": "trapinch",
            "babyForm": 0,
            "itemHeld": [
                {
                    "dbSymbol": "none",
                    "chance": 0
                },
                {
                    "dbSymbol": "none",
                    "chance": 0
                }
            ],
            "abilities": [
                "levitate",
                "levitate",
                "levitate"
            ],
            "frontOffsetY": 0,
            "moveSet": [
                {
                    "klass": "LevelLearnableMove",
                    "move": "bulldoze",
                    "level": 1
                },
                {
                    "klass": "LevelLearnableMove",
                    "move": "dragon_breath",
                    "level": 1
                },
                {
                    "klass": "LevelLearnableMove",
                    "move": "sand_attack",
                    "level": 1
                },
                {
                    "klass": "LevelLearnableMove",
                    "move": "supersonic",
                    "level": 1
                },
                {
                    "klass": "LevelLearnableMove",
                    "move": "mud_slap",
                    "level": 12
                },
                {
                    "klass": "LevelLearnableMove",
                    "move": "sand_tomb",
                    "level": 16
                },
                {
                    "klass": "LevelLearnableMove",
                    "move": "dragon_tail",
                    "level": 20
                },
                {
                    "klass": "LevelLearnableMove",
                    "move": "screech",
                    "level": 24
                },
                {
                    "klass": "LevelLearnableMove",
                    "move": "bug_buzz",
                    "level": 28
                },
                {
                    "klass": "LevelLearnableMove",
                    "move": "sandstorm",
                    "level": 32
                },
                {
                    "klass": "LevelLearnableMove",
                    "move": "earth_power",
                    "level": 38
                },
                {
                    "klass": "LevelLearnableMove",
                    "move": "earthquake",
                    "level": 44
                },
                {
                    "klass": "LevelLearnableMove",
                    "move": "uproar",
                    "level": 52
                },
                {
                    "klass": "LevelLearnableMove",
                    "move": "dragon_rush",
                    "level": 60
                },
                {
                    "klass": "LevelLearnableMove",
                    "move": "boomburst",
                    "level": 68
                },
                {
                    "klass": "EvolutionLearnableMove",
                    "move": "dragon_claw"
                },
                {
                    "klass": "TechLearnableMove",
                    "move": "take_down"
                },
                {
                    "klass": "TechLearnableMove",
                    "move": "agility"
                },
                {
                    "klass": "TechLearnableMove",
                    "move": "mud_slap"
                },
                {
                    "klass": "TechLearnableMove",
                    "move": "protect"
                },
                {
                    "klass": "TechLearnableMove",
                    "move": "struggle_bug"
                },
                {
                    "klass": "TechLearnableMove",
                    "move": "fire_spin"
                },
                {
                    "klass": "TechLearnableMove",
                    "move": "facade"
                },
                {
                    "klass": "TechLearnableMove",
                    "move": "aerial_ace"
                },
                {
                    "klass": "TechLearnableMove",
                    "move": "bulldoze"
                },
                {
                    "klass": "TechLearnableMove",
                    "move": "swift"
                },
                {
                    "klass": "TechLearnableMove",
                    "move": "mud_shot"
                },
                {
                    "klass": "TechLearnableMove",
                    "move": "rock_tomb"
                },
                {
                    "klass": "TechLearnableMove",
                    "move": "air_cutter"
                },
                {
                    "klass": "TechLearnableMove",
                    "move": "dragon_tail"
                },
                {
                    "klass": "TechLearnableMove",
                    "move": "endure"
                },
                {
                    "klass": "TechLearnableMove",
                    "move": "sunny_day"
                },
                {
                    "klass": "TechLearnableMove",
                    "move": "sandstorm"
                },
                {
                    "klass": "TechLearnableMove",
                    "move": "dig"
                },
                {
                    "klass": "TechLearnableMove",
                    "move": "u_turn"
                },
                {
                    "klass": "TechLearnableMove",
                    "move": "air_slash"
                },
                {
                    "klass": "TechLearnableMove",
                    "move": "body_slam"
                },
                {
                    "klass": "TechLearnableMove",
                    "move": "fire_punch"
                },
                {
                    "klass": "TechLearnableMove",
                    "move": "thunder_punch"
                },
                {
                    "klass": "TechLearnableMove",
                    "move": "sleep_talk"
                },
                {
                    "klass": "TechLearnableMove",
                    "move": "dragon_claw"
                },
                {
                    "klass": "TechLearnableMove",
                    "move": "rest"
                },
                {
                    "klass": "TechLearnableMove",
                    "move": "rock_slide"
                },
                {
                    "klass": "TechLearnableMove",
                    "move": "fly"
                },
                {
                    "klass": "TechLearnableMove",
                    "move": "dragon_dance"
                },
                {
                    "klass": "TechLearnableMove",
                    "move": "substitute"
                },
                {
                    "klass": "TechLearnableMove",
                    "move": "crunch"
                },
                {
                    "klass": "TechLearnableMove",
                    "move": "giga_drain"
                },
                {
                    "klass": "TechLearnableMove",
                    "move": "tailwind"
                },
                {
                    "klass": "TechLearnableMove",
                    "move": "dragon_pulse"
                },
                {
                    "klass": "TechLearnableMove",
                    "move": "stealth_rock"
                },
                {
                    "klass": "TechLearnableMove",
                    "move": "heat_wave"
                },
                {
                    "klass": "TechLearnableMove",
                    "move": "flamethrower"
                },
                {
                    "klass": "TechLearnableMove",
                    "move": "helping_hand"
                },
                {
                    "klass": "TechLearnableMove",
                    "move": "earth_power"
                },
                {
                    "klass": "TechLearnableMove",
                    "move": "fire_blast"
                },
                {
                    "klass": "TechLearnableMove",
                    "move": "earthquake"
                },
                {
                    "klass": "TechLearnableMove",
                    "move": "stone_edge"
                },
                {
                    "klass": "TechLearnableMove",
                    "move": "giga_impact"
                },
                {
                    "klass": "TechLearnableMove",
                    "move": "outrage"
                },
                {
                    "klass": "TechLearnableMove",
                    "move": "bug_buzz"
                },
                {
                    "klass": "TechLearnableMove",
                    "move": "hyper_beam"
                },
                {
                    "klass": "TechLearnableMove",
                    "move": "solar_beam"
                },
                {
                    "klass": "TechLearnableMove",
                    "move": "draco_meteor"
                },
                {
                    "klass": "TechLearnableMove",
                    "move": "tera_blast"
                },
                {
                    "klass": "TechLearnableMove",
                    "move": "sand_tomb"
                },
                {
                    "klass": "TechLearnableMove",
                    "move": "bug_bite"
                },
                {
                    "klass": "TechLearnableMove",
                    "move": "vacuum_wave"
                },
                {
                    "klass": "TechLearnableMove",
                    "move": "uproar"
                },
                {
                    "klass": "TechLearnableMove",
                    "move": "dual_wingbeat"
                },
                {
                    "klass": "TechLearnableMove",
                    "move": "scale_shot"
                },
                {
                    "klass": "TechLearnableMove",
                    "move": "double_edge"
                },
                {
                    "klass": "TechLearnableMove",
                    "move": "scorching_sands"
                },
                {
                    "klass": "TechLearnableMove",
                    "move": "throat_chop"
                },
                {
                    "klass": "TechLearnableMove",
                    "move": "breaking_swipe"
                },
                {
                    "klass": "TechLearnableMove",
                    "move": "dragon_cheer"
                },
                {
                    "klass": "TechLearnableMove",
                    "move": "alluring_voice"
                },
                {
                    "klass": "TechLearnableMove",
                    "move": "psychic_noise"
                }
            ],
            "resources": {
                "icon": "0330",
                "iconShiny": "",
                "front": "0330",
                "frontShiny": "0330",
                "back": "0330",
                "backShiny": "0330",
                "footprint": "0330",
                "character": "0330_00",
                "characterShiny": "0330s_00",
                "cry": "0330cry.ogg",
                "hasFemale": false
            }
        }
    ]
}