{
    "klass": "Specie",
    "id": 932,
    "dbSymbol": "nacli",
    "forms": [
        {
            "form": 0,
            "height": 0.4,
            "weight": 16.0,
            "type1": "rock",
            "type2": "__undef__",
            "baseHp": 55,
            "baseAtk": 55,
            "baseDfe": 75,
            "baseSpd": 25,
            "baseAts": 35,
            "baseDfs": 35,
            "evHp": 0,
            "evAtk": 0,
            "evDfe": 1,
            "evSpd": 0,
            "evAts": 0,
            "evDfs": 0,
            "evolutions": [
                {
                    "dbSymbol": "naclstack",
                    "form": 0,
                    "conditions": [
                        {
                            "type": "minLevel",
                            "value": 24
                        }
                    ]
                }
            ],
            "experienceType": 3,
            "baseExperience": 56,
            "baseLoyalty": 50,
            "catchRate": 255,
            "femaleRate": 50.0,
            "breedGroups": [
                10
            ],
            "hatchSteps": 2560,
            "babyDbSymbol": "nacli",
            "babyForm": 0,
            "itemHeld": [
                {
                    "dbSymbol": "none",
                    "chance": 0
                },
                {
                    "dbSymbol": "none",
                    "chance": 0
                }
            ],
            "abilities": [
                "purifying_salt",
                "sturdy",
                "clear_body"
            ],
            "frontOffsetY": 0,
            "moveSet": [
                {
                    "klass": "LevelLearnableMove",
                    "move": "harden",
                    "level": 1
                },
                {
                    "klass": "LevelLearnableMove",
                    "move": "tackle",
                    "level": 1
                },
                {
                    "klass": "LevelLearnableMove",
                    "move": "rock_throw",
                    "level": 5
                },
                {
                    "klass": "LevelLearnableMove",
                    "move": "mud_shot",
                    "level": 7
                },
                {
                    "klass": "LevelLearnableMove",
                    "move": "smack_down",
                    "level": 10
                },
                {
                    "klass": "LevelLearnableMove",
                    "move": "rock_polish",
                    "level": 13
                },
                {
                    "klass": "LevelLearnableMove",
                    "move": "headbutt",
                    "level": 16
                },
                {
                    "klass": "LevelLearnableMove",
                    "move": "iron_defense",
                    "level": 20
                },
                {
                    "klass": "LevelLearnableMove",
                    "move": "recover",
                    "level": 25
                },
                {
                    "klass": "LevelLearnableMove",
                    "move": "rock_slide",
                    "level": 30
                },
                {
                    "klass": "LevelLearnableMove",
                    "move": "stealth_rock",
                    "level": 33
                },
                {
                    "klass": "LevelLearnableMove",
                    "move": "heavy_slam",
                    "level": 35
                },
                {
                    "klass": "LevelLearnableMove",
                    "move": "earthquake",
                    "level": 40
                },
                {
                    "klass": "LevelLearnableMove",
                    "move": "stone_edge",
                    "level": 45
                },
                {
                    "klass": "BreedLearnableMove",
                    "move": "ancient_power"
                },
                {
                    "klass": "BreedLearnableMove",
                    "move": "curse"
                },
                {
                    "klass": "BreedLearnableMove",
                    "move": "fissure"
                },
                {
                    "klass": "BreedLearnableMove",
                    "move": "power_gem"
                },
                {
                    "klass": "TechLearnableMove",
                    "move": "take_down"
                },
                {
                    "klass": "TechLearnableMove",
                    "move": "protect"
                },
                {
                    "klass": "TechLearnableMove",
                    "move": "facade"
                },
                {
                    "klass": "TechLearnableMove",
                    "move": "bulldoze"
                },
                {
                    "klass": "TechLearnableMove",
                    "move": "mud_shot"
                },
                {
                    "klass": "TechLearnableMove",
                    "move": "endure"
                },
                {
                    "klass": "TechLearnableMove",
                    "move": "sunny_day"
                },
                {
                    "klass": "TechLearnableMove",
                    "move": "rain_dance"
                },
                {
                    "klass": "TechLearnableMove",
                    "move": "sandstorm"
                },
                {
                    "klass": "TechLearnableMove",
                    "move": "dig"
                },
                {
                    "klass": "TechLearnableMove",
                    "move": "zen_headbutt"
                },
                {
                    "klass": "TechLearnableMove",
                    "move": "body_slam"
                },
                {
                    "klass": "TechLearnableMove",
                    "move": "sleep_talk"
                },
                {
                    "klass": "TechLearnableMove",
                    "move": "stomping_tantrum"
                },
                {
                    "klass": "TechLearnableMove",
                    "move": "rest"
                },
                {
                    "klass": "TechLearnableMove",
                    "move": "rock_slide"
                },
                {
                    "klass": "TechLearnableMove",
                    "move": "flash_cannon"
                },
                {
                    "klass": "TechLearnableMove",
                    "move": "iron_head"
                },
                {
                    "klass": "TechLearnableMove",
                    "move": "power_gem"
                },
                {
                    "klass": "TechLearnableMove",
                    "move": "substitute"
                },
                {
                    "klass": "TechLearnableMove",
                    "move": "iron_defense"
                },
                {
                    "klass": "TechLearnableMove",
                    "move": "stealth_rock"
                },
                {
                    "klass": "TechLearnableMove",
                    "move": "heavy_slam"
                },
                {
                    "klass": "TechLearnableMove",
                    "move": "helping_hand"
                },
                {
                    "klass": "TechLearnableMove",
                    "move": "earth_power"
                },
                {
                    "klass": "TechLearnableMove",
                    "move": "earthquake"
                },
                {
                    "klass": "TechLearnableMove",
                    "move": "stone_edge"
                },
                {
                    "klass": "TechLearnableMove",
                    "move": "tera_blast"
                }
            ],
            "resources": {
                "icon": "0932",
                "iconShiny": "",
                "front": "0932",
                "frontShiny": "0932",
                "back": "0932",
                "backShiny": "0932",
                "footprint": "0932",
                "character": "0932_00",
                "characterShiny": "0932s_00",
                "cry": "0932cry.ogg",
                "hasFemale": false
            }
        }
    ]
}